conf_struct.py
ConfStruct-0.8.0.dist-info/DESCRIPTION.rst
ConfStruct-0.8.0.dist-info/METADATA
ConfStruct-0.8.0.dist-info/RECORD
ConfStruct-0.8.0.dist-info/WHEEL
ConfStruct-0.8.0.dist-info/metadata.json
ConfStruct-0.8.0.dist-info/top_level.txt
conf_struct/__init__.py
conf_struct/constructors.py
conf_struct/exceptions.py
conf_struct/exts.py
conf_struct/fields.py
conf_struct/structures.py
