Metadata-Version: 2.0
Name: ConfStruct
Version: 0.8.0
Summary: A parser and builder between python dictionary and "length-body" binary data.
Home-page: https://github.com/kinegratii/ConfStruct
Author: kinegratii
Author-email: kinegratii@gmail.com
License: MIT
Keywords: struct binary pack unpack
Platform: UNKNOWN
Classifier: Development Status :: 4 - Beta
Classifier: Programming Language :: Python :: 2
Classifier: Programming Language :: Python :: 2.7
Classifier: Programming Language :: Python :: 3
Classifier: Programming Language :: Python :: 3.4
Classifier: Programming Language :: Python :: 3.5
Classifier: Programming Language :: Python :: 3.6
Classifier: Intended Audience :: Developers
Classifier: License :: OSI Approved :: MIT License
Classifier: Topic :: Software Development :: Libraries
Classifier: Topic :: Utilities
Requires-Dist: six
